clip_interrogator/__init__.py
clip_interrogator/clip_interrogator.py
clip_interrogator/data/artists.txt
clip_interrogator/data/flavors_sfw.txt
clip_interrogator/data/mediums.txt
clip_interrogator/data/movements.txt
clip_interrogator/data/negative.txt
clip_interrogator_sfw-0.6.1.dist-info/licenses/LICENSE
clip_interrogator_sfw-0.6.1.dist-info/METADATA
clip_interrogator_sfw-0.6.1.dist-info/WHEEL
clip_interrogator_sfw-0.6.1.dist-info/top_level.txt
clip_interrogator_sfw-0.6.1.dist-info/RECORD
