Metadata-Version: 2.4
Name: clip-interrogator-sfw
Version: 0.6.1
Summary: Generate a prompt from an image (SFW version)
Home-page: https://github.com/cpietsch/clip-interrogator-sfw
Author: pharmapsychotic, chrispie
Author-email: cpietsch@gmail.com
License: MIT
Keywords: blip,clip,prompt-engineering,stable-diffusion,text-to-image,sfw
Classifier: Intended Audience :: Developers
Classifier: Intended Audience :: Science/Research
Classifier: License :: OSI Approved :: MIT License
Classifier: Topic :: Education
Classifier: Topic :: Scientific/Engineering
Classifier: Topic :: Scientific/Engineering :: Artificial Intelligence
License-File: LICENSE
Requires-Dist: torch>=1.13.0
Requires-Dist: torchvision
Requires-Dist: Pillow
Requires-Dist: requests
Requires-Dist: safetensors
Requires-Dist: tqdm
Requires-Dist: open_clip_torch
Requires-Dist: accelerate
Requires-Dist: transformers>=4.27.1
Provides-Extra: dev
Requires-Dist: pytest; extra == "dev"
Dynamic: author
Dynamic: author-email
Dynamic: classifier
Dynamic: description
Dynamic: description-content-type
Dynamic: home-page
Dynamic: keywords
Dynamic: license
Dynamic: license-file
Dynamic: provides-extra
Dynamic: requires-dist
Dynamic: summary
